bump_pydantic/__init__.py
bump_pydantic/__main__.py
bump_pydantic/glob_helpers.py
bump_pydantic/main.py
bump_pydantic/py.typed
bump_pydantic/.github/workflows/ci.yml
bump_pydantic/codemods/__init__.py
bump_pydantic/codemods/add_default_none.py
bump_pydantic/codemods/class_def_visitor.py
bump_pydantic/codemods/con_func.py
bump_pydantic/codemods/custom_types.py
bump_pydantic/codemods/field.py
bump_pydantic/codemods/replace_config.py
bump_pydantic/codemods/replace_generic_model.py
bump_pydantic/codemods/replace_imports.py
bump_pydantic/codemods/root_model.py
bump_pydantic/codemods/validator.py
bump_pydantic-0.7.0.dist-info/METADATA
bump_pydantic-0.7.0.dist-info/WHEEL
bump_pydantic-0.7.0.dist-info/entry_points.txt
bump_pydantic-0.7.0.dist-info/licenses/LICENSE.txt
bump_pydantic-0.7.0.dist-info/RECORD
