Metadata-Version: 2.1
Name: bump-pydantic
Version: 0.7.0
Summary: Convert Pydantic from V1 to V2 ♻
Project-URL: Documentation, https://github.com/pydantic/bump-pydantic#readme
Project-URL: Issues, https://github.com/pydantic/bump-pydantic/issues
Project-URL: Source, https://github.com/pydantic/bump-pydantic
Author-email: Marcelo Trylesinski <marcelotryle@gmail.com>
License-Expression: MIT
License-File: LICENSE.txt
Classifier: Development Status :: 4 - Beta
Classifier: Framework :: Pydantic
Classifier: Programming Language :: Python
Classifier: Programming Language :: Python :: 3.8
Classifier: Programming Language :: Python :: 3.9
Classifier: Programming Language :: Python :: 3.10
Classifier: Programming Language :: Python :: 3.11
Classifier: Programming Language :: Python :: Implementation :: CPython
Classifier: Programming Language :: Python :: Implementation :: PyPy
Requires-Python: >=3.8
Requires-Dist: libcst
Requires-Dist: rich
Requires-Dist: typer>=0.7.0
Requires-Dist: typing-extensions
